clearskies_aws/__init__.py
clearskies_aws/actions/__init__.py
clearskies_aws/actions/action_aws.py
clearskies_aws/actions/assume_role.py
clearskies_aws/actions/ses.py
clearskies_aws/actions/sns.py
clearskies_aws/actions/sqs.py
clearskies_aws/actions/step_function.py
clearskies_aws/backends/__init__.py
clearskies_aws/backends/backend.py
clearskies_aws/backends/dynamo_db_backend.py
clearskies_aws/backends/dynamo_db_condition_parser.py
clearskies_aws/backends/dynamo_db_parti_ql_backend.py
clearskies_aws/backends/sqs_backend.py
clearskies_aws/configs/__init__.py
clearskies_aws/contexts/__init__.py
clearskies_aws/contexts/cli_web_socket_mock.py
clearskies_aws/contexts/lambda_alb.py
clearskies_aws/contexts/lambda_api_gateway.py
clearskies_aws/contexts/lambda_api_gateway_web_socket.py
clearskies_aws/contexts/lambda_invoke.py
clearskies_aws/contexts/lambda_sns.py
clearskies_aws/contexts/lambda_sqs_standard.py
clearskies_aws/cursors/__init__.py
clearskies_aws/cursors/iam/__init__.py
clearskies_aws/cursors/iam/rds_mysql.py
clearskies_aws/cursors/port_forwarding/__init__.py
clearskies_aws/cursors/port_forwarding/ssm.py
clearskies_aws/di/__init__.py
clearskies_aws/di/aws_additional_config_auto_import.py
clearskies_aws/di/inject/__init__.py
clearskies_aws/di/inject/boto3.py
clearskies_aws/di/inject/boto3_session.py
clearskies_aws/di/inject/parameter_store.py
clearskies_aws/endpoints/__init__.py
clearskies_aws/endpoints/secrets_manager_rotation.py
clearskies_aws/endpoints/simple_body_routing.py
clearskies_aws/input_outputs/__init__.py
clearskies_aws/input_outputs/cli_web_socket_mock.py
clearskies_aws/input_outputs/lambda_alb.py
clearskies_aws/input_outputs/lambda_api_gateway.py
clearskies_aws/input_outputs/lambda_api_gateway_web_socket.py
clearskies_aws/input_outputs/lambda_input_output.py
clearskies_aws/input_outputs/lambda_invoke.py
clearskies_aws/input_outputs/lambda_sns.py
clearskies_aws/input_outputs/lambda_sqs_standard.py
clearskies_aws/mocks/__init__.py
clear_skies_aws-2.0.9.dist-info/METADATA
clear_skies_aws-2.0.9.dist-info/WHEEL
clear_skies_aws-2.0.9.dist-info/licenses/LICENSE
clear_skies_aws-2.0.9.dist-info/RECORD
