Metadata-Version: 2.4
Name: clear-skies-aws
Version: 2.0.9
Summary: clearskies bindings for working in AWS
Project-URL: Repository, https://github.com/clearskies-py/clearskies-aws
Project-URL: Issues, https://github.com/clearskies-py/clearskies-aws/issues
Project-URL: Changelog, https://github.com/clearskies-py/clearskies-aws/blob/main/CHANGELOG.md
Project-URL: Documentation, https://clearskies.info/modules/clearskies-aws/
Author: tnijboer
Author-email: Conor Mancone <cmancone@gmail.com>
License-Expression: MIT
License-File: LICENSE
Classifier: Development Status :: 5 - Production/Stable
Classifier: Intended Audience :: Developers
Classifier: License :: OSI Approved :: MIT License
Classifier: Programming Language :: Python :: 3
Requires-Python: <4.0,>=3.11
Requires-Dist: boto3<2.0.0,>=1.26.148
Requires-Dist: clear-skies<3.0.0,>=2.0.20
Requires-Dist: types-boto3[dynamodb,secretsmanager,ses,sns,sqs,ssm,stepfunctions]<2.0.0,>=1.38.13
Provides-Extra: akeyless
Requires-Dist: akeyless-cloud-id<0.5.0,>=0.2.3; extra == 'akeyless'
Requires-Dist: akeyless<6.0.0,>=5.0.0; extra == 'akeyless'
Provides-Extra: mysql
Requires-Dist: clear-skies[mysql]; extra == 'mysql'
Provides-Extra: ses
Requires-Dist: jinja2<4.0.0,>=3.1.2; extra == 'ses'
